bitkub/__init__.py
bitkub/bitkub.py
bitkub/constants.py
bitkub/decorators.py
bitkub/error.py
bitkub/request.py
bitkub/tests.py
bitkub-1.1.0.dist-info/METADATA
bitkub-1.1.0.dist-info/WHEEL
bitkub-1.1.0.dist-info/top_level.txt
bitkub-1.1.0.dist-info/RECORD
