Metadata-Version: 2.1
Name: bitkub
Version: 1.1.0
Summary: A Python library for Bitkub API
Home-page: https://github.com/sang-sakarin/bitkub
Author: sang_sakarin
Author-email: sang_sakarin@outlook.com
License: sang_sakarin
Keywords: bitkub bitkub-python bitkub-python-sdk
Platform: UNKNOWN
Requires-Dist: requests
